fast_ssim/__init__.py
fast_ssim/_core.py
fast_ssim/resources/libssim.so
fast_ssim/resources/ssim.dll
fast_ssim-1.1.0.dist-info/licenses/LICENSE
fast_ssim-1.1.0.dist-info/METADATA
fast_ssim-1.1.0.dist-info/WHEEL
fast_ssim-1.1.0.dist-info/top_level.txt
fast_ssim-1.1.0.dist-info/RECORD
