Metadata-Version: 2.4
Name: Fast-SSIM
Version: 1.1.0
Summary: Fast SSIM and PSNR algorithms for Python.
Author: Tim Lodemann
License-Expression: MIT
Project-URL: Homepage, https://github.com/timminator/Fast-SSIM
Project-URL: documentation, https://github.com/timminator/Fast-SSIM/blob/master/README.md
Project-URL: Repository, https://github.com/timminator/Fast-SSIM.git
Project-URL: Issues, https://github.com/timminator/Fast-SSIM/issues
Keywords: ssim,psnr,image quality,image comparison,image processing
Classifier: Intended Audience :: Developers
Classifier: Operating System :: Microsoft :: Windows
Classifier: Operating System :: POSIX :: Linux
Classifier: Programming Language :: Python :: 3
Classifier: Topic :: Scientific/Engineering :: Image Processing
Requires-Python: >=3.9
License-File: LICENSE
Requires-Dist: numpy
Dynamic: license-file
